bodo_jupyterlab/__init__.py
bodo_jupyterlab/_version.py
bodo_jupyterlab/cluster_terminal.py
bodo_jupyterlab/config.py
bodo_jupyterlab/config_vars.py
bodo_jupyterlab/handlers.py
bodo_jupyterlab/helpers.py
bodo_jupyterlab/platform.py
bodo_jupyterlab/remote_ikernels_manager.py
bodo_jupyterlab/ssh_keys_manager.py
bodo_jupyterlab/labextension/package.json
bodo_jupyterlab/labextension/static/114.e3beb30b42f7dc21c954.js
bodo_jupyterlab/labextension/static/27.6d719126bd35ac79f1f4.js
bodo_jupyterlab/labextension/static/580.578ff6c213110b4f097e.js
bodo_jupyterlab/labextension/static/590.d8217373bb2a506f327b.js
bodo_jupyterlab/labextension/static/590.d8217373bb2a506f327b.js.LICENSE.txt
bodo_jupyterlab/labextension/static/640.233dddcdb33406dbdb69.js
bodo_jupyterlab/labextension/static/640.233dddcdb33406dbdb69.js.LICENSE.txt
bodo_jupyterlab/labextension/static/653.8b6f48ff6260f6eaa791.js
bodo_jupyterlab/labextension/static/909.9a20bc1b575d7bf853ba.js
bodo_jupyterlab/labextension/static/990.efcf42890c51105f1579.js
bodo_jupyterlab/labextension/static/990.efcf42890c51105f1579.js.LICENSE.txt
bodo_jupyterlab/labextension/static/remoteEntry.ad321d001e44ab1fdf71.js
bodo_jupyterlab/labextension/static/style.js
bodo_jupyterlab/labextension/static/third-party-licenses.json
bodo_jupyterlab-1.18.2.data/data/etc/jupyter/jupyter_notebook_config.d/bodo_jupyterlab.json
bodo_jupyterlab-1.18.2.data/data/etc/jupyter/jupyter_server_config.d/bodo_jupyterlab.json
bodo_jupyterlab-1.18.2.data/data/share/jupyter/labextensions/bodo-jupyterlab/install.json
bodo_jupyterlab-1.18.2.data/data/share/jupyter/labextensions/bodo-jupyterlab/package.json
bodo_jupyterlab-1.18.2.data/data/share/jupyter/labextensions/bodo-jupyterlab/static/114.e3beb30b42f7dc21c954.js
bodo_jupyterlab-1.18.2.data/data/share/jupyter/labextensions/bodo-jupyterlab/static/27.6d719126bd35ac79f1f4.js
bodo_jupyterlab-1.18.2.data/data/share/jupyter/labextensions/bodo-jupyterlab/static/580.578ff6c213110b4f097e.js
bodo_jupyterlab-1.18.2.dist-info/LICENSE
bodo_jupyterlab-1.18.2.dist-info/METADATA
bodo_jupyterlab-1.18.2.dist-info/WHEEL
bodo_jupyterlab-1.18.2.dist-info/top_level.txt
bodo_jupyterlab-1.18.2.dist-info/RECORD
