Metadata-Version: 2.1
Name: bodo-jupyterlab
Version: 1.18.2
Summary: A JupyterLab extension.
Home-page: https://github.com/Bodo-inc/jupyterlab-extensions
Author: Bodo, Inc.
Author-email: noreply@bodo.ai
License: BSD-3-Clause
Keywords: Jupyter,JupyterLab,JupyterLab3,Bodo
Platform: Linux
Platform: Mac OS X
Platform: Windows
Classifier: License :: OSI Approved :: BSD License
Classifier: Programming Language :: Python
Classifier: Programming Language :: Python :: 3
Classifier: Programming Language :: Python :: 3.6
Classifier: Programming Language :: Python :: 3.7
Classifier: Programming Language :: Python :: 3.8
Classifier: Programming Language :: Python :: 3.9
Classifier: Framework :: Jupyter
Classifier: Framework :: Jupyter :: JupyterLab
Classifier: Framework :: Jupyter :: JupyterLab :: 3
Classifier: Framework :: Jupyter :: JupyterLab :: Extensions
Classifier: Framework :: Jupyter :: JupyterLab :: Extensions :: Prebuilt
Requires-Python: >=3.8
License-File: LICENSE
Requires-Dist: jupyterlab ==3.4.*
Requires-Dist: jupyter-packaging >=0.12.3
Requires-Dist: cachetools >=4.2.4
Requires-Dist: remote-ikernel >=0.7.0
Requires-Dist: terminado ==0.15.0
Requires-Dist: arrow ==1.3.0
